Workbook

Sheet Assumptions
A1: NovaSaaS Inc.: Model Assumptions and Key Drivers
A2: All figures in $mm unless noted. Blue cells are hardcoded inputs; black cells are formulas.
A3: Assumption / Driver | B3: FY2022A | C3: FY2023A | D3: FY2024A | E3: FY2025E | F3: FY2026E | G3: FY2027E | H3: FY2028E | I3: FY2029E
A4: REVENUE ASSUMPTIONS
A5: ARR, Beginning of Period ($mm) | B5: 120 | C5: 185 | D5: 268 | E5: N/A | F5: N/A | G5: N/A | H5: N/A | I5: N/A
A6: Net New ARR ($mm) | B6: 65 | C6: 83 | D6: 102 | E6: N/A | F6: N/A | G6: N/A | H6: N/A | I6: N/A
A7: ARR Growth Rate | B7: 0.18 | C7: 0.18 | D7: 0.18 | E7: 0.3 | F7: 0.27 | G7: 0.24 | H7: 0.21 | I7: 0.18
A8: ARR, End of Period ($mm) | B8: 185 | C8: 268 | D8: 370 | E8: =D8*(1+E7) -> 481 | F8: =E8*(1+F7) -> 610.87 | G8: =F8*(1+G7) -> 757.4788 | H8: =G8*(1+H7) -> 916.54935 | I8: =H8*(1+I7) -> 1081.5282
A9: Revenue Recognition (% of ARR) | B9: 0.88 | C9: 0.89 | D9: 0.9 | E9: 0.9 | F9: 0.9 | G9: 0.91 | H9: 0.91 | I9: 0.91
A10: Total Revenue ($mm) | B10: 106 | C10: 160 | D10: 234 | E10: =E8*E9 -> 432.9 | F10: =F8*F9 -> 549.783 | G10: =G8*G9 -> 689.30571 | H10: =H8*H9 -> 834.05991 | I10: =I8*I9 -> 984.19069
A11: MARGIN AND COST ASSUMPTIONS
A12: Gross Margin % | B12: 0.68 | C12: 0.7 | D12: 0.72 | E12: 0.73 | F12: 0.74 | G12: 0.75 | H12: 0.76 | I12: 0.77
A13: S&M % of Revenue | B13: 0.42 | C13: 0.38 | D13: 0.35 | E13: 0.33 | F13: 0.31 | G13: 0.29 | H13: 0.27 | I13: 0.25
A14: R&D % of Revenue | B14: 0.18 | C14: 0.17 | D14: 0.16 | E14: 0.15 | F14: 0.15 | G14: 0.14 | H14: 0.14 | I14: 0.13
A15: G&A % of Revenue | B15: 0.12 | C15: 0.11 | D15: 0.1 | E15: 0.09 | F15: 0.09 | G15: 0.08 | H15: 0.08 | I15: 0.08
A16: D&A % of Revenue | B16: 0.03 | C16: 0.03 | D16: 0.03 | E16: 0.03 | F16: 0.03 | G16: 0.03 | H16: 0.03 | I16: 0.03
A17: Effective Tax Rate | B17: 0.21 | C17: 0.21 | D17: 0.21 | E17: 0.21 | F17: 0.21 | G17: 0.21 | H17: 0.21 | I17: 0.21
A18: BALANCE SHEET AND WORKING CAPITAL ASSUMPTIONS
A19: DSO (Days) | B19: 55 | C19: 52 | D19: 50 | E19: 48 | F19: 46 | G19: 44 | H19: 42 | I19: 40
A20: DPO (Days) | B20: 30 | C20: 30 | D20: 32 | E20: 32 | F20: 33 | G20: 33 | H20: 34 | I20: 34
A21: Deferred Revenue (days) | B21: 90 | C21: 90 | D21: 92 | E21: 92 | F21: 93 | G21: 93 | H21: 94 | I21: 94
A22: Capex % of Revenue | B22: 0.04 | C22: 0.04 | D22: 0.03 | E22: 0.03 | F22: 0.03 | G22: 0.03 | H22: 0.02 | I22: 0.02
A23: DCF VALUATION ASSUMPTIONS
A24: WACC | B24: 0.1 | C24: (Discount rate: risk-free rate + equity risk premium + size/specific risk)
A25: Terminal Growth Rate | B25: 0.03 | C25: (Long-term perpetuity growth rate; should be at or below nominal GDP growth)
A26: Net Debt / (Cash) ($mm) | B26: -85 | C26: (Negative value indicates net cash position)
A27: Diluted Shares Outstanding (mm) | B27: 125

Sheet Income Statement
A1: NovaSaaS Inc.: Income Statement
A2: All figures in USD millions. Hypothetical SaaS company for portfolio demonstration purposes.
B3: FY2022A | C3: FY2023A | D3: FY2024A | E3: FY2025E | F3: FY2026E | G3: FY2027E | H3: FY2028E | I3: FY2029E
A4: REVENUE
A5: Subscription Revenue | B5: 95 | C5: 144 | D5: 211 | E5: =Assumptions!E10*0.92 -> 398.268 | F5: =Assumptions!F10*0.92 -> 505.80036 | G5: =Assumptions!G10*0.92 -> 634.16125 | H5: =Assumptions!H10*0.92 -> 767.33511 | I5: =Assumptions!I10*0.92 -> 905.45543
A6: Professional Services | B6: 11 | C6: 16 | D6: 23 | E6: =Assumptions!E10*0.08 -> 34.632 | F6: =Assumptions!F10*0.08 -> 43.98264 | G6: =Assumptions!G10*0.08 -> 55.144457 | H6: =Assumptions!H10*0.08 -> 66.724793 | I6: =Assumptions!I10*0.08 -> 78.735255
A7: Total Revenue | B7: =SUM(B5:B6) -> 106 | C7: =SUM(C5:C6) -> 160 | D7: =SUM(D5:D6) -> 234 | E7: =SUM(E5:E6) -> 432.9 | F7: =SUM(F5:F6) -> 549.783 | G7: =SUM(G5:G6) -> 689.30571 | H7: =SUM(H5:H6) -> 834.05991 | I7: =SUM(I5:I6) -> 984.19069
A8: COST OF REVENUE
A9: Cost of Revenue | B9: =B7*(1-Assumptions!B12) -> 33.92 | C9: =C7*(1-Assumptions!C12) -> 48 | D9: =D7*(1-Assumptions!D12) -> 65.52 | E9: =E7*(1-Assumptions!E12) -> 116.883 | F9: =F7*(1-Assumptions!F12) -> 142.94358 | G9: =G7*(1-Assumptions!G12) -> 172.32643 | H9: =H7*(1-Assumptions!H12) -> 200.17438 | I9: =I7*(1-Assumptions!I12) -> 226.36386
A10: Gross Profit | B10: =B7-B9 -> 72.08 | C10: =C7-C9 -> 112 | D10: =D7-D9 -> 168.48 | E10: =E7-E9 -> 316.017 | F10: =F7-F9 -> 406.83942 | G10: =G7-G9 -> 516.97928 | H10: =H7-H9 -> 633.88553 | I10: =I7-I9 -> 757.82683
A11: Gross Margin % | B11: =B10/B7 -> 0.68 | C11: =C10/C7 -> 0.7 | D11: =D10/D7 -> 0.72 | E11: =E10/E7 -> 0.73 | F11: =F10/F7 -> 0.74 | G11: =G10/G7 -> 0.75 | H11: =H10/H7 -> 0.76 | I11: =I10/I7 -> 0.77
A12: OPERATING EXPENSES
A13: Sales and Marketing | B13: =B7*Assumptions!B13 -> 44.52 | C13: =C7*Assumptions!C13 -> 60.8 | D13: =D7*Assumptions!D13 -> 81.9 | E13: =E7*Assumptions!E13 -> 142.857 | F13: =F7*Assumptions!F13 -> 170.43273 | G13: =G7*Assumptions!G13 -> 199.89866 | H13: =H7*Assumptions!H13 -> 225.19617 | I13: =I7*Assumptions!I13 -> 246.04767
A14: Research and Development | B14: =B7*Assumptions!B14 -> 19.08 | C14: =C7*Assumptions!C14 -> 27.2 | D14: =D7*Assumptions!D14 -> 37.44 | E14: =E7*Assumptions!E14 -> 64.935 | F14: =F7*Assumptions!F14 -> 82.46745 | G14: =G7*Assumptions!G14 -> 96.502799 | H14: =H7*Assumptions!H14 -> 116.76839 | I14: =I7*Assumptions!I14 -> 127.94479
A15: General and Administrative | B15: =B7*Assumptions!B15 -> 12.72 | C15: =C7*Assumptions!C15 -> 17.6 | D15: =D7*Assumptions!D15 -> 23.4 | E15: =E7*Assumptions!E15 -> 38.961 | F15: =F7*Assumptions!F15 -> 49.48047 | G15: =G7*Assumptions!G15 -> 55.144457 | H15: =H7*Assumptions!H15 -> 66.724793 | I15: =I7*Assumptions!I15 -> 78.735255
A16: Depreciation and Amortization | B16: =B7*Assumptions!B16 -> 3.18 | C16: =C7*Assumptions!C16 -> 4.8 | D16: =D7*Assumptions!D16 -> 7.02 | E16: =E7*Assumptions!E16 -> 12.987 | F16: =F7*Assumptions!F16 -> 16.49349 | G16: =G7*Assumptions!G16 -> 20.679171 | H16: =H7*Assumptions!H16 -> 25.021797 | I16: =I7*Assumptions!I16 -> 29.525721
A17: Total OpEx | B17: =SUM(B13:B16) -> 79.5 | C17: =SUM(C13:C16) -> 110.4 | D17: =SUM(D13:D16) -> 149.76 | E17: =SUM(E13:E16) -> 259.74 | F17: =SUM(F13:F16) -> 318.87414 | G17: =SUM(G13:G16) -> 372.22508 | H17: =SUM(H13:H16) -> 433.71115 | I17: =SUM(I13:I16) -> 482.25344
A18: EBIT (Operating Income) | B18: =B10-B17 -> -7.42 | C18: =C10-C17 -> 1.6 | D18: =D10-D17 -> 18.72 | E18: =E10-E17 -> 56.277 | F18: =F10-F17 -> 87.96528 | G18: =G10-G17 -> 144.7542 | H18: =H10-H17 -> 200.17438 | I18: =I10-I17 -> 275.57339
A19: EBIT Margin % | B19: =IFERROR(B18/B7,0) -> -0.07 | C19: =IFERROR(C18/C7,0) -> 0.01 | D19: =IFERROR(D18/D7,0) -> 0.08 | E19: =IFERROR(E18/E7,0) -> 0.13 | F19: =IFERROR(F18/F7,0) -> 0.16 | G19: =IFERROR(G18/G7,0) -> 0.21 | H19: =IFERROR(H18/H7,0) -> 0.24 | I19: =IFERROR(I18/I7,0) -> 0.28
A20: NON-OPERATING ITEMS
A21: Interest Income / (Expense) | B21: 2 | C21: 2 | D21: 2 | E21: 3 | F21: 3 | G21: 3 | H21: 3 | I21: 3
A22: Pre-Tax Income | B22: =B18+B21 -> -5.42 | C22: =C18+C21 -> 3.6 | D22: =D18+D21 -> 20.72 | E22: =E18+E21 -> 59.277 | F22: =F18+F21 -> 90.96528 | G22: =G18+G21 -> 147.7542 | H22: =H18+H21 -> 203.17438 | I22: =I18+I21 -> 278.57339
A23: Income Tax Expense | B23: =MAX(0,B22*Assumptions!B17) -> 0 | C23: =MAX(0,C22*Assumptions!B17) -> 0.756 | D23: =MAX(0,D22*Assumptions!B17) -> 4.3512 | E23: =MAX(0,E22*Assumptions!B17) -> 12.44817 | F23: =MAX(0,F22*Assumptions!B17) -> 19.102709 | G23: =MAX(0,G22*Assumptions!B17) -> 31.028382 | H23: =MAX(0,H22*Assumptions!B17) -> 42.666619 | I23: =MAX(0,I22*Assumptions!B17) -> 58.500413
A24: Net Income | B24: =B22-B23 -> -5.42 | C24: =C22-C23 -> 2.844 | D24: =D22-D23 -> 16.3688 | E24: =E22-E23 -> 46.82883 | F24: =F22-F23 -> 71.862571 | G24: =G22-G23 -> 116.72582 | H24: =H22-H23 -> 160.50776 | I24: =I22-I23 -> 220.07298
A25: Net Margin % | B25: =IFERROR(B24/B7,0) -> -0.051132075 | C25: =IFERROR(C24/C7,0) -> 0.017775 | D25: =IFERROR(D24/D7,0) -> 0.069952137 | E25: =IFERROR(E24/E7,0) -> 0.10817471 | F25: =IFERROR(F24/F7,0) -> 0.13071079 | G25: =IFERROR(G24/G7,0) -> 0.16933824 | H25: =IFERROR(H24/H7,0) -> 0.19244152 | I25: =IFERROR(I24/I7,0) -> 0.22360807
A26: EBITDA BRIDGE
A27: EBITDA | B27: =B18+B16 -> -4.24 | C27: =C18+C16 -> 6.4 | D27: =D18+D16 -> 25.74 | E27: =E18+E16 -> 69.264 | F27: =F18+F16 -> 104.45877 | G27: =G18+G16 -> 165.43337 | H27: =H18+H16 -> 225.19617 | I27: =I18+I16 -> 305.09911
A28: EBITDA Margin % | B28: =IFERROR(B27/B7,0) -> -0.04 | C28: =IFERROR(C27/C7,0) -> 0.04 | D28: =IFERROR(D27/D7,0) -> 0.11 | E28: =IFERROR(E27/E7,0) -> 0.16 | F28: =IFERROR(F27/F7,0) -> 0.19 | G28: =IFERROR(G27/G7,0) -> 0.24 | H28: =IFERROR(H27/H7,0) -> 0.27 | I28: =IFERROR(I27/I7,0) -> 0.31
A29: YoY Revenue Growth | B29: N/A | C29: =IFERROR(C7/B7-1,0) -> 0.50943396 | D29: =IFERROR(D7/C7-1,0) -> 0.4625 | E29: =IFERROR(E7/D7-1,0) -> 0.85 | F29: =IFERROR(F7/E7-1,0) -> 0.27 | G29: =IFERROR(G7/F7-1,0) -> 0.25377778 | H29: =IFERROR(H7/G7-1,0) -> 0.21 | I29: =IFERROR(I7/H7-1,0) -> 0.18

Sheet Cash Flow Statement
A1: NovaSaaS Inc.: Cash Flow Statement
B2: FY2022A | C2: FY2023A | D2: FY2024A | E2: FY2025E | F2: FY2026E | G2: FY2027E | H2: FY2028E | I2: FY2029E
A3: OPERATING ACTIVITIES
A4: Net Income | B4: ='Income Statement'!B24 -> -5.42 | C4: ='Income Statement'!C24 -> 2.844 | D4: ='Income Statement'!D24 -> 16.3688 | E4: ='Income Statement'!E24 -> 46.82883 | F4: ='Income Statement'!F24 -> 71.862571 | G4: ='Income Statement'!G24 -> 116.72582 | H4: ='Income Statement'!H24 -> 160.50776 | I4: ='Income Statement'!I24 -> 220.07298
A5: Add: Depreciation and Amortization | B5: ='Income Statement'!B16 -> 3.18 | C5: ='Income Statement'!C16 -> 4.8 | D5: ='Income Statement'!D16 -> 7.02 | E5: ='Income Statement'!E16 -> 12.987 | F5: ='Income Statement'!F16 -> 16.49349 | G5: ='Income Statement'!G16 -> 20.679171 | H5: ='Income Statement'!H16 -> 25.021797 | I5: ='Income Statement'!I16 -> 29.525721
A6: (Increase) / Decrease in Accounts Receivable | B6: 0 | C6: =-('Income Statement'!C7/365*Assumptions!C19-'Income Statement'!B7/365*Assumptions!B19) -> -6.8219178 | D6: =-('Income Statement'!D7/365*Assumptions!D19-'Income Statement'!C7/365*Assumptions!C19) -> -9.260274 | E6: =-('Income Statement'!E7/365*Assumptions!E19-'Income Statement'!D7/365*Assumptions!D19) -> -24.874521 | F6: =-('Income Statement'!F7/365*Assumptions!F19-'Income Statement'!E7/365*Assumptions!E19) -> -12.358405 | G6: =-('Income Statement'!G7/365*Assumptions!G19-'Income Statement'!F7/365*Assumptions!F19) -> -13.806666 | H6: =-('Income Statement'!H7/365*Assumptions!H19-'Income Statement'!G7/365*Assumptions!G19) -> -12.87963 | I6: =-('Income Statement'!I7/365*Assumptions!I19-'Income Statement'!H7/365*Assumptions!H19) -> -11.882497
A7: Increase / (Decrease) in Deferred Revenue | B7: 0 | C7: ='Income Statement'!C7/365*Assumptions!C21-'Income Statement'!B7/365*Assumptions!B21 -> 13.315068 | D7: ='Income Statement'!D7/365*Assumptions!D21-'Income Statement'!C7/365*Assumptions!C21 -> 19.528767 | E7: ='Income Statement'!E7/365*Assumptions!E21-'Income Statement'!D7/365*Assumptions!D21 -> 50.133699 | F7: ='Income Statement'!F7/365*Assumptions!F21-'Income Statement'!E7/365*Assumptions!E21 -> 30.967175 | G7: ='Income Statement'!G7/365*Assumptions!G21-'Income Statement'!F7/365*Assumptions!F21 -> 35.549621 | H7: ='Income Statement'!H7/365*Assumptions!H21-'Income Statement'!G7/365*Assumptions!G21 -> 39.167672 | I7: ='Income Statement'!I7/365*Assumptions!I21-'Income Statement'!H7/365*Assumptions!H21 -> 38.663818
A8: Increase / (Decrease) in Accounts Payable | B8: 0 | C8: ='Income Statement'!C9/365*Assumptions!C20-'Income Statement'!B9/365*Assumptions!B20 -> 1.1572603 | D8: ='Income Statement'!D9/365*Assumptions!D20-'Income Statement'!C9/365*Assumptions!C20 -> 1.7990137 | E8: ='Income Statement'!E9/365*Assumptions!E20-'Income Statement'!D9/365*Assumptions!D20 -> 4.5030575 | F8: ='Income Statement'!F9/365*Assumptions!F20-'Income Statement'!E9/365*Assumptions!E20 -> 2.6763894 | G8: ='Income Statement'!G9/365*Assumptions!G20-'Income Statement'!F9/365*Assumptions!F20 -> 2.6565314 | H8: ='Income Statement'!H9/365*Assumptions!H20-'Income Statement'!G9/365*Assumptions!G20 -> 3.0661829 | I8: ='Income Statement'!I9/365*Assumptions!I20-'Income Statement'!H9/365*Assumptions!H20 -> 2.4395681
A9: Cash from Operations | B9: =SUM(B4:B8) -> -2.24 | C9: =SUM(C4:C8) -> 15.294411 | D9: =SUM(D4:D8) -> 35.456307 | E9: =SUM(E4:E8) -> 89.578066 | F9: =SUM(F4:F8) -> 109.64122 | G9: =SUM(G4:G8) -> 161.80447 | H9: =SUM(H4:H8) -> 214.88378 | I9: =SUM(I4:I8) -> 278.81959
A10: INVESTING ACTIVITIES
A11: Capital Expenditures | B11: =-('Income Statement'!B7*Assumptions!B22) -> -4.24 | C11: =-('Income Statement'!C7*Assumptions!C22) -> -6.4 | D11: =-('Income Statement'!D7*Assumptions!D22) -> -7.02 | E11: =-('Income Statement'!E7*Assumptions!E22) -> -12.987 | F11: =-('Income Statement'!F7*Assumptions!F22) -> -16.49349 | G11: =-('Income Statement'!G7*Assumptions!G22) -> -20.679171 | H11: =-('Income Statement'!H7*Assumptions!H22) -> -16.681198 | I11: =-('Income Statement'!I7*Assumptions!I22) -> -19.683814
A12: Cash from Investing | B12: =B11 -> -4.24 | C12: =C11 -> -6.4 | D12: =D11 -> -7.02 | E12: =E11 -> -12.987 | F12: =F11 -> -16.49349 | G12: =G11 -> -20.679171 | H12: =H11 -> -16.681198 | I12: =I11 -> -19.683814
A13: FINANCING ACTIVITIES
A14: Share Repurchases / (Issuances) | B14: 0 | C14: 0 | D14: 0 | E14: 0 | F14: 0 | G14: 0 | H14: 0 | I14: 0
A15: Debt Issuance / (Repayment) | B15: 0 | C15: 0 | D15: 0 | E15: 0 | F15: 0 | G15: 0 | H15: 0 | I15: 0
A16: Cash from Financing | B16: =SUM(B14:B15) -> 0 | C16: =SUM(C14:C15) -> 0 | D16: =SUM(D14:D15) -> 0 | E16: =SUM(E14:E15) -> 0 | F16: =SUM(F14:F15) -> 0 | G16: =SUM(G14:G15) -> 0 | H16: =SUM(H14:H15) -> 0 | I16: =SUM(I14:I15) -> 0
A17: Net Change in Cash | B17: =B9+B12+B16 -> -6.48 | C17: =C9+C12+C16 -> 8.894411 | D17: =D9+D12+D16 -> 28.436307 | E17: =E9+E12+E16 -> 76.591066 | F17: =F9+F12+F16 -> 93.14773 | G17: =G9+G12+G16 -> 141.1253 | H17: =H9+H12+H16 -> 198.20258 | I17: =I9+I12+I16 -> 259.13578
A18: Beginning Cash | B18: 45 | C18: =B19 -> 38.52 | D18: =C19 -> 47.414411 | E18: =D19 -> 75.850718 | F18: =E19 -> 152.44178 | G18: =F19 -> 245.58951 | H18: =G19 -> 386.71482 | I18: =H19 -> 584.9174
A19: Ending Cash | B19: =B18+B17 -> 38.52 | C19: =C18+C17 -> 47.414411 | D19: =D18+D17 -> 75.850718 | E19: =E18+E17 -> 152.44178 | F19: =F18+F17 -> 245.58951 | G19: =G18+G17 -> 386.71482 | H19: =H18+H17 -> 584.9174 | I19: =I18+I17 -> 844.05318
A20: Free Cash Flow (CFO less Capex) | B20: =B9+B11 -> -6.48 | C20: =C9+C11 -> 8.894411 | D20: =D9+D11 -> 28.436307 | E20: =E9+E11 -> 76.591066 | F20: =F9+F11 -> 93.14773 | G20: =G9+G11 -> 141.1253 | H20: =H9+H11 -> 198.20258 | I20: =I9+I11 -> 259.13578
A21: FCF Margin % | B21: =IFERROR(B20/'Income Statement'!B7,0) -> -0.061132075 | C21: =IFERROR(C20/'Income Statement'!C7,0) -> 0.055590068 | D21: =IFERROR(D20/'Income Statement'!D7,0) -> 0.12152268 | E21: =IFERROR(E20/'Income Statement'!E7,0) -> 0.17692554 | F21: =IFERROR(F20/'Income Statement'!F7,0) -> 0.16942636 | G21: =IFERROR(G20/'Income Statement'!G7,0) -> 0.20473543 | H21: =IFERROR(H20/'Income Statement'!H7,0) -> 0.23763591 | I21: =IFERROR(I20/'Income Statement'!I7,0) -> 0.26329834

Sheet DCF Valuation
A1: NovaSaaS Inc.: DCF Valuation
B2: FY2025E | C2: FY2026E | D2: FY2027E | E2: FY2028E | F2: FY2029E
A3: FREE CASH FLOW PROJECTIONS
A4: Free Cash Flow ($mm) | B4: ='Cash Flow Statement'!B20 -> -6.48 | C4: ='Cash Flow Statement'!C20 -> 8.894411 | D4: ='Cash Flow Statement'!D20 -> 28.436307 | E4: ='Cash Flow Statement'!E20 -> 76.591066 | F4: ='Cash Flow Statement'!F20 -> 93.14773
A5: Discount Period | B5: 1 | C5: 2 | D5: 3 | E5: 4 | F5: 5
A6: Discount Factor | B6: =1/(1+Assumptions!B24)^1 -> 0.90909091 | C6: =1/(1+Assumptions!B24)^2 -> 0.82644628 | D6: =1/(1+Assumptions!B24)^3 -> 0.7513148 | E6: =1/(1+Assumptions!B24)^4 -> 0.68301346 | F6: =1/(1+Assumptions!B24)^5 -> 0.62092132
A7: Present Value of FCF | B7: =B4*B6 -> -5.8909091 | C7: =C4*C6 -> 7.3507529 | D7: =D4*D6 -> 21.364618 | E7: =E4*E6 -> 52.312728 | F7: =F4*F6 -> 57.837412
A8: TERMINAL VALUE
A9: Terminal Year FCF ($mm) | B9: ='Cash Flow Statement'!F20 -> 93.14773
A10: Terminal Value (Gordon Growth Model) | B10: =B9*(1+Assumptions!B25)/(Assumptions!B24-Assumptions!B25) -> 1370.6023
A11: PV of Terminal Value | B11: =B10/(1+Assumptions!B24)^5 -> 851.03621
A12: ENTERPRISE VALUE BRIDGE
A13: Sum of PV of FCFs ($mm) | B13: =SUM(B7:F7) -> 132.9746
A14: PV of Terminal Value ($mm) | B14: =B11 -> 851.03621
A15: Enterprise Value ($mm) | B15: =B13+B14 -> 984.01081
A16: Less: Net Debt / (Plus: Net Cash) ($mm) | B16: =-Assumptions!B26 -> 85
A17: Equity Value ($mm) | B17: =B15+B16 -> 1069.0108
A18: Diluted Shares Outstanding (mm) | B18: =Assumptions!B27 -> 125
A19: Implied Share Price | B19: =IFERROR(B17/B18,0) -> 8.5520865
A21: SENSITIVITY ANALYSIS: IMPLIED SHARE PRICE
A22: WACC | B22: TGR ↓ \ WACC → | C22: 0.08 | D22: 0.09 | E22: 0.1 | F22: 0.11 | G22: 0.12
B23: 0.02 | C23: =IFERROR((('Cash Flow Statement'!F20*(1+$B23)/(C$22-$B23)/(1+C$22)^5)+SUMPRODUCT('Cash Flow Statement'!B20:F20,1/(1+C$22)^{1,2,3,4,5})-Assumptions!B26)/Assumptions!B27,0) -> 10.452816 | D23: =IFERROR((('Cash Flow Statement'!F20*(1+$B23)/(D$22-$B23)/(1+D$22)^5)+SUMPRODUCT('Cash Flow Statement'!B20:F20,1/(1+D$22)^{1,2,3,4,5})-Assumptions!B26)/Assumptions!B27,0) -> 8.8435757 | E23: =IFERROR((('Cash Flow Statement'!F20*(1+$B23)/(E$22-$B23)/(1+E$22)^5)+SUMPRODUCT('Cash Flow Statement'!B20:F20,1/(1+E$22)^{1,2,3,4,5})-Assumptions!B26)/Assumptions!B27,0) -> 7.6432128 | F23: =IFERROR((('Cash Flow Statement'!F20*(1+$B23)/(F$22-$B23)/(1+F$22)^5)+SUMPRODUCT('Cash Flow Statement'!B20:F20,1/(1+F$22)^{1,2,3,4,5})-Assumptions!B26)/Assumptions!B27,0) -> 6.7151704 | G23: =IFERROR((('Cash Flow Statement'!F20*(1+$B23)/(G$22-$B23)/(1+G$22)^5)+SUMPRODUCT('Cash Flow Statement'!B20:F20,1/(1+G$22)^{1,2,3,4,5})-Assumptions!B26)/Assumptions!B27,0) -> 5.9775274
B24: 0.025 | C24: =IFERROR((('Cash Flow Statement'!F20*(1+$B24)/(C$22-$B24)/(1+C$22)^5)+SUMPRODUCT('Cash Flow Statement'!B20:F20,1/(1+C$22)^{1,2,3,4,5})-Assumptions!B26)/Assumptions!B27,0) -> 11.282711 | D24: =IFERROR((('Cash Flow Statement'!F20*(1+$B24)/(D$22-$B24)/(1+D$22)^5)+SUMPRODUCT('Cash Flow Statement'!B20:F20,1/(1+D$22)^{1,2,3,4,5})-Assumptions!B26)/Assumptions!B27,0) -> 9.4236917 | E24: =IFERROR((('Cash Flow Statement'!F20*(1+$B24)/(E$22-$B24)/(1+E$22)^5)+SUMPRODUCT('Cash Flow Statement'!B20:F20,1/(1+E$22)^{1,2,3,4,5})-Assumptions!B26)/Assumptions!B27,0) -> 8.0673539 | F24: =IFERROR((('Cash Flow Statement'!F20*(1+$B24)/(F$22-$B24)/(1+F$22)^5)+SUMPRODUCT('Cash Flow Statement'!B20:F20,1/(1+F$22)^{1,2,3,4,5})-Assumptions!B26)/Assumptions!B27,0) -> 7.0360033 | G24: =IFERROR((('Cash Flow Statement'!F20*(1+$B24)/(G$22-$B24)/(1+G$22)^5)+SUMPRODUCT('Cash Flow Statement'!B20:F20,1/(1+G$22)^{1,2,3,4,5})-Assumptions!B26)/Assumptions!B27,0) -> 6.2267783
B25: 0.03 | C25: =IFERROR((('Cash Flow Statement'!F20*(1+$B25)/(C$22-$B25)/(1+C$22)^5)+SUMPRODUCT('Cash Flow Statement'!B20:F20,1/(1+C$22)^{1,2,3,4,5})-Assumptions!B26)/Assumptions!B27,0) -> 12.278585 | D25: =IFERROR((('Cash Flow Statement'!F20*(1+$B25)/(D$22-$B25)/(1+D$22)^5)+SUMPRODUCT('Cash Flow Statement'!B20:F20,1/(1+D$22)^{1,2,3,4,5})-Assumptions!B26)/Assumptions!B27,0) -> 10.100494 | E25: =IFERROR((('Cash Flow Statement'!F20*(1+$B25)/(E$22-$B25)/(1+E$22)^5)+SUMPRODUCT('Cash Flow Statement'!B20:F20,1/(1+E$22)^{1,2,3,4,5})-Assumptions!B26)/Assumptions!B27,0) -> 8.5520865 | F25: =IFERROR((('Cash Flow Statement'!F20*(1+$B25)/(F$22-$B25)/(1+F$22)^5)+SUMPRODUCT('Cash Flow Statement'!B20:F20,1/(1+F$22)^{1,2,3,4,5})-Assumptions!B26)/Assumptions!B27,0) -> 7.3969404 | G25: =IFERROR((('Cash Flow Statement'!F20*(1+$B25)/(G$22-$B25)/(1+G$22)^5)+SUMPRODUCT('Cash Flow Statement'!B20:F20,1/(1+G$22)^{1,2,3,4,5})-Assumptions!B26)/Assumptions!B27,0) -> 6.5037236
B26: 0.035 | C26: =IFERROR((('Cash Flow Statement'!F20*(1+$B26)/(C$22-$B26)/(1+C$22)^5)+SUMPRODUCT('Cash Flow Statement'!B20:F20,1/(1+C$22)^{1,2,3,4,5})-Assumptions!B26)/Assumptions!B27,0) -> 13.495765 | D26: =IFERROR((('Cash Flow Statement'!F20*(1+$B26)/(D$22-$B26)/(1+D$22)^5)+SUMPRODUCT('Cash Flow Statement'!B20:F20,1/(1+D$22)^{1,2,3,4,5})-Assumptions!B26)/Assumptions!B27,0) -> 10.900351 | E26: =IFERROR((('Cash Flow Statement'!F20*(1+$B26)/(E$22-$B26)/(1+E$22)^5)+SUMPRODUCT('Cash Flow Statement'!B20:F20,1/(1+E$22)^{1,2,3,4,5})-Assumptions!B26)/Assumptions!B27,0) -> 9.1113933 | F26: =IFERROR((('Cash Flow Statement'!F20*(1+$B26)/(F$22-$B26)/(1+F$22)^5)+SUMPRODUCT('Cash Flow Statement'!B20:F20,1/(1+F$22)^{1,2,3,4,5})-Assumptions!B26)/Assumptions!B27,0) -> 7.8060023 | G26: =IFERROR((('Cash Flow Statement'!F20*(1+$B26)/(G$22-$B26)/(1+G$22)^5)+SUMPRODUCT('Cash Flow Statement'!B20:F20,1/(1+G$22)^{1,2,3,4,5})-Assumptions!B26)/Assumptions!B27,0) -> 6.8132507
B27: 0.04 | C27: =IFERROR((('Cash Flow Statement'!F20*(1+$B27)/(C$22-$B27)/(1+C$22)^5)+SUMPRODUCT('Cash Flow Statement'!B20:F20,1/(1+C$22)^{1,2,3,4,5})-Assumptions!B26)/Assumptions!B27,0) -> 15.01724 | D27: =IFERROR((('Cash Flow Statement'!F20*(1+$B27)/(D$22-$B27)/(1+D$22)^5)+SUMPRODUCT('Cash Flow Statement'!B20:F20,1/(1+D$22)^{1,2,3,4,5})-Assumptions!B26)/Assumptions!B27,0) -> 11.860179 | E27: =IFERROR((('Cash Flow Statement'!F20*(1+$B27)/(E$22-$B27)/(1+E$22)^5)+SUMPRODUCT('Cash Flow Statement'!B20:F20,1/(1+E$22)^{1,2,3,4,5})-Assumptions!B26)/Assumptions!B27,0) -> 9.763918 | F27: =IFERROR((('Cash Flow Statement'!F20*(1+$B27)/(F$22-$B27)/(1+F$22)^5)+SUMPRODUCT('Cash Flow Statement'!B20:F20,1/(1+F$22)^{1,2,3,4,5})-Assumptions!B26)/Assumptions!B27,0) -> 8.2735017 | G27: =IFERROR((('Cash Flow Statement'!F20*(1+$B27)/(G$22-$B27)/(1+G$22)^5)+SUMPRODUCT('Cash Flow Statement'!B20:F20,1/(1+G$22)^{1,2,3,4,5})-Assumptions!B26)/Assumptions!B27,0) -> 7.1614688
A28: Base case highlighted in yellow (WACC = 10%, Terminal Growth Rate = 3%). WACC and TGR header cells are live inputs — update to refresh the table.

Sheet Scenario Analysis
A1: NovaSaaS Inc.: Scenario Analysis
A2: Metric | B2: Bear Case | C2: Base Case | D2: Bull Case
A3: ARR Growth Rate (FY2025E) | B3: 0.2 | C3: 0.3 | D3: 0.42
A4: Gross Margin (FY2025E) | B4: 0.7 | C4: 0.73 | D4: 0.76
A5: EBITDA Margin (FY2025E) | B5: -0.05 | C5: 0.05 | D5: 0.14
A6: FY2025E Revenue ($mm) | B6: =ROUND(Assumptions!D8*(1+B3)*Assumptions!E9,0) -> 400 | C6: =ROUND(Assumptions!D8*(1+C3)*Assumptions!E9,0) -> 433 | D6: =ROUND(Assumptions!D8*(1+D3)*Assumptions!E9,0) -> 473
A7: FY2025E EBITDA ($mm) | B7: =ROUND(B6*B5,0) -> -20 | C7: =ROUND(C6*C5,0) -> 22 | D7: =ROUND(D6*D5,0) -> 66
A8: Implied EV / Revenue | B8: 4 | C8: 6 | D8: 9
A9: Implied Share Price | B9: =IFERROR((B6*B8-Assumptions!B26)/Assumptions!B27,0) -> 13.48 | C9: =IFERROR((C6*C8-Assumptions!B26)/Assumptions!B27,0) -> 21.464 | D9: =IFERROR((D6*D8-Assumptions!B26)/Assumptions!B27,0) -> 34.736
A11: Scenario Assumptions:
A12: Bear Case: Macro headwinds and elevated churn compress growth; elongated sales cycles and competitive pressure weigh on margins.
A13: Base Case: Steady ARR growth with gradual margin expansion; net revenue retention holds at approximately 115%.
A14: Bull Case: Accelerated enterprise adoption and strong product-led growth; upsell momentum drives net revenue retention above 125%.
